pywfa/.DS_Store
pywfa/WFA_wrap.c
pywfa/WFA_wrap.pxd
pywfa/__init__.py
pywfa/align.c
pywfa/align.cpython-310-darwin.so
pywfa/align.cpython-38-darwin.so
pywfa/align.cpython-39-darwin.so
pywfa/align.pxd
pywfa/align.pyx
pywfa/WFA2_lib/alignment/Makefile
pywfa/WFA2_lib/alignment/affine2p_penalties.c
pywfa/WFA2_lib/alignment/affine2p_penalties.h
pywfa/WFA2_lib/alignment/affine_penalties.c
pywfa/WFA2_lib/alignment/affine_penalties.h
pywfa/WFA2_lib/alignment/cigar.c
pywfa/WFA2_lib/alignment/cigar.h
pywfa/WFA2_lib/alignment/linear_penalties.h
pywfa/WFA2_lib/alignment/score_matrix.c
pywfa/WFA2_lib/alignment/score_matrix.h
pywfa/WFA2_lib/build/affine2p_penalties.o
pywfa/WFA2_lib/build/affine_penalties.o
pywfa/WFA2_lib/build/bitmap.o
pywfa/WFA2_lib/build/cigar.o
pywfa/WFA2_lib/build/commons.o
pywfa/WFA2_lib/build/dna_text.o
pywfa/WFA2_lib/build/heatmap.o
pywfa/WFA2_lib/build/mm_allocator.o
pywfa/WFA2_lib/build/mm_stack.o
pywfa/WFA2_lib/build/profiler_counter.o
pywfa/WFA2_lib/build/profiler_timer.o
pywfa/WFA2_lib/build/score_matrix.o
pywfa/WFA2_lib/build/sequence_buffer.o
pywfa/WFA2_lib/build/string_padded.o
pywfa/WFA2_lib/build/vector.o
pywfa/WFA2_lib/build/wavefront.o
pywfa/WFA2_lib/build/wavefront_align.o
pywfa/WFA2_lib/build/wavefront_aligner.o
pywfa/WFA2_lib/build/wavefront_attributes.o
pywfa/WFA2_lib/build/wavefront_backtrace.o
pywfa/WFA2_lib/build/wavefront_backtrace_buffer.o
pywfa/WFA2_lib/build/wavefront_backtrace_offload.o
pywfa/WFA2_lib/build/wavefront_components.o
pywfa/WFA2_lib/build/wavefront_compute.o
pywfa/WFA2_lib/build/wavefront_compute_affine.o
pywfa/WFA2_lib/build/wavefront_compute_affine2p.o
pywfa/WFA2_lib/build/wavefront_compute_edit.o
pywfa/WFA2_lib/build/wavefront_compute_linear.o
pywfa/WFA2_lib/build/wavefront_debug.o
pywfa/WFA2_lib/build/wavefront_display.o
pywfa/WFA2_lib/build/wavefront_extend.o
pywfa/WFA2_lib/build/wavefront_heuristic.o
pywfa/WFA2_lib/build/wavefront_pcigar.o
pywfa/WFA2_lib/build/wavefront_penalties.o
pywfa-0.2.7.dist-info/LICENSE.md
pywfa-0.2.7.dist-info/METADATA
pywfa-0.2.7.dist-info/WHEEL
pywfa-0.2.7.dist-info/top_level.txt
pywfa-0.2.7.dist-info/RECORD
