Metadata-Version: 2.1
Name: pywfa
Version: 0.2.7
Summary: Align sequences using WFA2-lib
Home-page: https://github.com/kcleal/pywfa
Author: Kez Cleal
Author-email: clealk@cardiff.ac.uk
License: MIT
Platform: UNKNOWN
Requires-Python: >=3.7
Requires-Dist: cython
